translator_template/__init__.py
translator_template/app.py
translator_template/data/test.docx
translator_template/generator.py
translator_template/parse.py
translator_template/templates.py
translator_template/tests/__init__.py
translator_template/tests/data/test.txt
translator_template/tests/test_generator.py
translator_template/tests/test_parse.py
translator_template-0.2.4.dist-info/entry_points.txt
translator_template-0.2.4.dist-info/LICENSE
translator_template-0.2.4.dist-info/WHEEL
translator_template-0.2.4.dist-info/METADATA
translator_template-0.2.4.dist-info/RECORD
