Metadata-Version: 2.1
Name: translator-template
Version: 0.2.4
Summary: Utility for generating a Microsoft Word file from a simple document description, for translators.
License: MIT
Author: Chris Thrasher
Author-email: cthrash@github.com
Requires-Python: >=3.7,<4.0
Classifier: License :: OSI Approved :: MIT License
Classifier: Programming Language :: Python :: 3
Classifier: Programming Language :: Python :: 3.10
Classifier: Programming Language :: Python :: 3.7
Classifier: Programming Language :: Python :: 3.8
Classifier: Programming Language :: Python :: 3.9
